Full Adder Functional Verilog Example/full_adder.v
module full_adder (x, y, cin, s, cout);
    
    input x, y, cin;
    output s, cout;

    assign s = x ^ y ^ cin;
    assign cout = (x & y) | (cin & x) | (cin & y);

endmodule


module tb;

     reg x, y, cin;
     wire s, cout;

     full_adder f1(x, y, cin, s, cout);

     initial begin
        $dumpfile("full_adder.vcd");
        $dumpvars(0, tb);
     end

     initial begin
        x = 0; y = 0; cin = 0; #10;
        x = 0; y = 0; cin = 1; #10;
        x = 0; y = 1; cin = 0; #10;
        x = 0; y = 1; cin = 1; #10;
        x = 1; y = 0; cin = 0; #10;
        x = 1; y = 0; cin = 1; #10;
        x = 1; y = 1; cin = 0; #10;
        x = 1; y = 1; cin = 1; #10;
     end

endmodule

Full Adder Functional Verilog Example/full_adder.vcd
$date
	Tue Jun  2 19:00:31 2026
$end
$version
	Icarus Verilog
$end
$timescale
	1s
$end
$scope module tb $end
$var wire 1 ! s $end
$var wire 1 " cout $end
$var reg 1 # cin $end
$var reg 1 $ x $end
$var reg 1 % y $end
$scope module f1 $end
$var wire 1 # cin $end
$var wire 1 " cout $end
$var wire 1 ! s $end
$var wire 1 $ x $end
$var wire 1 % y $end
$upscope $end
$upscope $end
$enddefinitions $end
#0
$dumpvars
0%
0$
0#
0"
0!
$end
#10
1!
1#
#20
0#
1%
#30
1"
0!
1#
#40
0"
1!
0#
0%
1$
#50
1"
0!
1#
#60
0#
1%
#70
1!
1#
